{"offset":-0.215,"totalnotes":172,"BPM":141,"Notes":[{"types":1,"measure":4,"time":0},{"types":1,"measure":5,"time":0},{"types":1,"measure":5,"time":24},{"types":1,"measure":6,"time":0},{"types":1,"measure":7,"time":0},{"types":1,"measure":8,"time":0},{"types":1,"measure":8,"time":24},{"types":1,"measure":9,"time":0},{"types":1,"measure":9,"time":24},{"types":1,"measure":9,"time":36},{"types":1,"measure":10,"time":0},{"types":1,"measure":10,"time":24},{"types":1,"measure":11,"time":0},{"types":3,"measure":12,"time":0},{"types":3,"measure":13,"time":0},{"types":1,"measure":14,"time":0},{"types":1,"measure":14,"time":24},{"types":1,"measure":14,"time":36},{"types":1,"measure":15,"time":0},{"types":1,"measure":15,"time":24},{"types":1,"measure":15,"time":36},{"types":1,"measure":16,"time":0},{"types":1,"measure":16,"time":24},{"types":1,"measure":16,"time":36},{"types":1,"measure":17,"time":0},{"types":1,"measure":17,"time":36},{"types":1,"measure":18,"time":0},{"types":1,"measure":18,"time":12},{"types":1,"measure":18,"time":24},{"types":1,"measure":19,"time":0},{"types":1,"measure":19,"time":12},{"types":1,"measure":19,"time":18},{"types":1,"measure":19,"time":24},{"types":1,"measure":20,"time":0},{"types":1,"measure":20,"time":12},{"types":1,"measure":20,"time":24},{"types":1,"measure":21,"time":0},{"types":1,"measure":21,"time":12},{"types":1,"measure":21,"time":18},{"types":1,"measure":21,"time":24},{"types":1,"measure":22,"time":0},{"types":1,"measure":22,"time":24},{"types":1,"measure":23,"time":36},{"types":1,"measure":23,"time":42},{"types":1,"measure":24,"time":0},{"types":1,"measure":24,"time":24},{"types":1,"measure":25,"time":36},{"types":1,"measure":25,"time":42},{"types":1,"measure":26,"time":0},{"types":1,"measure":26,"time":12},{"types":1,"measure":26,"time":24},{"types":1,"measure":27,"time":0},{"types":1,"measure":27,"time":12},{"types":1,"measure":27,"time":18},{"types":1,"measure":27,"time":24},{"types":1,"measure":28,"time":0},{"types":1,"measure":28,"time":12},{"types":1,"measure":28,"time":24},{"types":1,"measure":29,"time":0},{"types":1,"measure":29,"time":12},{"types":1,"measure":29,"time":18},{"types":1,"measure":29,"time":24},{"types":1,"measure":30,"time":0},{"types":1,"measure":30,"time":24},{"types":1,"measure":31,"time":36},{"types":1,"measure":31,"time":42},{"types":1,"measure":32,"time":0},{"types":1,"measure":32,"time":24},{"types":1,"measure":34,"time":0},{"types":1,"measure":34,"time":24},{"types":1,"measure":34,"time":36},{"types":1,"measure":34,"time":42},{"types":1,"measure":35,"time":0},{"types":1,"measure":35,"time":36},{"types":1,"measure":35,"time":42},{"types":1,"measure":36,"time":0},{"types":1,"measure":36,"time":24},{"types":1,"measure":36,"time":36},{"types":1,"measure":36,"time":42},{"types":1,"measure":38,"time":0},{"types":1,"measure":38,"time":24},{"types":1,"measure":38,"time":36},{"types":1,"measure":38,"time":42},{"types":1,"measure":39,"time":0},{"types":1,"measure":39,"time":36},{"types":1,"measure":39,"time":42},{"types":3,"measure":40,"time":0},{"types":3,"measure":41,"time":0},{"types":1,"measure":42,"time":0},{"types":1,"measure":42,"time":24},{"types":1,"measure":42,"time":36},{"types":1,"measure":43,"time":0},{"types":1,"measure":43,"time":24},{"types":1,"measure":43,"time":36},{"types":1,"measure":44,"time":0},{"types":1,"measure":44,"time":12},{"types":2,"measure":44,"time":24},{"types":1,"measure":45,"time":0},{"types":1,"measure":45,"time":6},{"types":1,"measure":45,"time":12},{"types":1,"measure":45,"time":24},{"types":1,"measure":45,"time":36},{"types":1,"measure":46,"time":12},{"types":1,"measure":46,"time":24},{"types":1,"measure":47,"time":0},{"types":1,"measure":47,"time":6},{"types":1,"measure":47,"time":12},{"types":1,"measure":47,"time":24},{"types":1,"measure":47,"time":36},{"types":1,"measure":48,"time":12},{"types":1,"measure":48,"time":24},{"types":1,"measure":49,"time":0},{"types":1,"measure":49,"time":12},{"types":1,"measure":50,"time":0},{"types":1,"measure":50,"time":12},{"types":1,"measure":50,"time":18},{"types":1,"measure":50,"time":24},{"types":1,"measure":51,"time":0},{"types":1,"measure":51,"time":12},{"types":1,"measure":52,"time":0},{"types":1,"measure":52,"time":12},{"types":1,"measure":52,"time":18},{"types":1,"measure":52,"time":24},{"types":1,"measure":53,"time":0},{"types":1,"measure":53,"time":6},{"types":1,"measure":53,"time":12},{"types":1,"measure":53,"time":24},{"types":1,"measure":53,"time":36},{"types":1,"measure":54,"time":12},{"types":1,"measure":54,"time":24},{"types":1,"measure":55,"time":0},{"types":1,"measure":55,"time":6},{"types":1,"measure":55,"time":12},{"types":1,"measure":55,"time":24},{"types":1,"measure":55,"time":36},{"types":1,"measure":56,"time":12},{"types":1,"measure":56,"time":24},{"types":1,"measure":57,"time":0},{"types":1,"measure":57,"time":12},{"types":1,"measure":58,"time":0},{"types":1,"measure":58,"time":12},{"types":1,"measure":58,"time":18},{"types":1,"measure":58,"time":24},{"types":1,"measure":59,"time":0},{"types":1,"measure":59,"time":12},{"types":1,"measure":61,"time":0},{"types":1,"measure":61,"time":24},{"types":1,"measure":61,"time":36},{"types":1,"measure":61,"time":42},{"types":1,"measure":62,"time":0},{"types":1,"measure":62,"time":36},{"types":1,"measure":62,"time":42},{"types":1,"measure":63,"time":0},{"types":1,"measure":63,"time":24},{"types":1,"measure":63,"time":36},{"types":1,"measure":63,"time":42},{"types":1,"measure":65,"time":0},{"types":1,"measure":65,"time":24},{"types":1,"measure":65,"time":36},{"types":1,"measure":65,"time":42},{"types":1,"measure":66,"time":0},{"types":1,"measure":66,"time":36},{"types":1,"measure":66,"time":42},{"types":3,"measure":67,"time":0},{"types":3,"measure":68,"time":0},{"types":1,"measure":69,"time":0},{"types":1,"measure":69,"time":24},{"types":1,"measure":69,"time":36},{"types":1,"measure":70,"time":0},{"types":1,"measure":70,"time":24},{"types":1,"measure":70,"time":36},{"types":3,"measure":72,"time":0}],"renda":[{"start":{"measure":23,"time":0},"end":{"measure":23,"time":24}},{"start":{"measure":25,"time":0},"end":{"measure":25,"time":24}},{"start":{"measure":31,"time":0},"end":{"measure":31,"time":24}},{"start":{"measure":33,"time":0},"end":{"measure":33,"time":24}},{"start":{"measure":37,"time":0},"end":{"measure":37,"time":18}},{"start":{"measure":37,"time":24},"end":{"measure":37,"time":42}},{"start":{"measure":60,"time":0},"end":{"measure":60,"time":24}},{"start":{"measure":64,"time":0},"end":{"measure":64,"time":18}},{"start":{"measure":64,"time":24},"end":{"measure":64,"time":42}}]}